testjaehyun/__init__.py
testjaehyun/__version__.py
testjaehyun/plus.py
testjaehyun-0.0.3.dist-info/METADATA
testjaehyun-0.0.3.dist-info/WHEEL
testjaehyun-0.0.3.dist-info/top_level.txt
testjaehyun-0.0.3.dist-info/RECORD
