Metadata-Version: 2.1
Name: testjaehyun
Version: 0.0.3
Summary: test package distribution
Home-page: UNKNOWN
Author: Jaehyun Yim
Author-email: jhyim@cerestechs.com
License: UNKNOWN
Platform: UNKNOWN
Requires-Python: >=3.6
